perfait/__init__.py
perfait/cli.py
perfait/scripts/perfait_scripts/measure_command.py
perfait/scripts/perfait_scripts/perfait/go.mod
perfait/scripts/perfait_scripts/perfait/perfait.cs
perfait/scripts/perfait_scripts/perfait/perfait.go
perfait/scripts/perfait_scripts/perfait/perfait.hpp
perfait/scripts/perfait_scripts/perfait/perfait.java
perfait/scripts/perfait_scripts/perfait/perfait.js
perfait/scripts/perfait_scripts/perfait/perfait.php
perfait/scripts/perfait_scripts/perfait/perfait.py
perfait/scripts/perfait_scripts/perfait/perfait.rb
perfait/tasks/init.py
perfait-0.1.1.dist-info/LICENSE
perfait-0.1.1.dist-info/METADATA
perfait-0.1.1.dist-info/WHEEL
perfait-0.1.1.dist-info/entry_points.txt
perfait-0.1.1.dist-info/top_level.txt
perfait-0.1.1.dist-info/RECORD
