Metadata-Version: 2.2
Name: perfait
Version: 0.1.1
Summary: Performance survey comparison tool
Author-email: mskz-3110 <mskz.saito@gmail.com>
Project-URL: Homepage, https://github.com/mskz-3110/perfait
Project-URL: Issues, https://github.com/mskz-3110/perfait/issues
Classifier: Programming Language :: Python :: 3
Classifier: License :: OSI Approved :: MIT License
Classifier: Operating System :: OS Independent
Requires-Python: >=3.13
License-File: LICENSE
Requires-Dist: graspgraph
